{
    "certifications": [
        {
            "certificationID": {
                "idValue": "EXCEL01"
            },
            "externalReference": "EXCEL01",
            "certificationDescription": "Excel basis",
            "itemID": "EXCEL01"
        },
        {
            "certificationID": {
                "idValue": "RBA"
            },
            "externalReference": "RBA",
            "certificationDescription": "Motorrijbewijs A",
            "itemID": "RBA"
        },
        {
            "certificationID": {
                "idValue": "RBA1"
            },
            "externalReference": "RBA1",
            "certificationDescription": "Motorrijbewijs A1 125cc en max 11kW",
            "itemID": "RBA1"
        },
        {
            "certificationID": {
                "idValue": "RBA2"
            },
            "externalReference": "RBA2",
            "certificationDescription": "Motorrijbewijs A2 max 35kW",
            "itemID": "RBA2"
        },
        {
            "certificationID": {
                "idValue": "RBAM"
            },
            "externalReference": "RBAM",
            "certificationDescription": "Rijbewijs AM bromfiets,scooter etc.",
            "itemID": "RBAM"
        },
        {
            "certificationID": {
                "idValue": "RBB"
            },
            "externalReference": "RBB",
            "certificationDescription": "Autorijbewijs B",
            "itemID": "RBB"
        },
        {
            "certificationID": {
                "idValue": "RBBE"
            },
            "externalReference": "RBBE",
            "certificationDescription": "Rijbewijs BE auto met aanhanger",
            "itemID": "RBBE"
        },
        {
            "certificationID": {
                "idValue": "RBC"
            },
            "externalReference": "RBC",
            "certificationDescription": "Vrachtwagenrijbewijs C",
            "itemID": "RBC"
        },
        {
            "certificationID": {
                "idValue": "RBC1"
            },
            "externalReference": "RBC1",
            "certificationDescription": "Rijbewijs C1 voor lichte vrachtwagen (max 7.5t)",
            "itemID": "RBC1"
        },
        {
            "certificationID": {
                "idValue": "RBC1E"
            },
            "externalReference": "RBC1E",
            "certificationDescription": "Rijbewijs C1E voor vrachtwagen(C1) met aanhanger",
            "itemID": "RBC1E"
        },
        {
            "certificationID": {
                "idValue": "RBCE"
            },
            "externalReference": "RBCE",
            "certificationDescription": "Rijbewijs CE vrachtwagen(C) met aanhanger",
            "itemID": "RBCE"
        },
        {
            "certificationID": {
                "idValue": "RBD"
            },
            "externalReference": "RBD",
            "certificationDescription": "Busrijbewijs D",
            "itemID": "RBD"
        },
        {
            "certificationID": {
                "idValue": "RBD1"
            },
            "externalReference": "RBD1",
            "certificationDescription": "Rijbwijs D1 voor kleine bus (8-16 pers)",
            "itemID": "RBD1"
        },
        {
            "certificationID": {
                "idValue": "RBD1E"
            },
            "externalReference": "RBD1E",
            "certificationDescription": "Rijbwijs D1E voor bus(D1) met aanhanger",
            "itemID": "RBD1E"
        },
        {
            "certificationID": {
                "idValue": "RBDE"
            },
            "externalReference": "RBDE",
            "certificationDescription": "Rijbwijs DE voor bus(D) met aanhanger",
            "itemID": "RBDE"
        },
        {
            "certificationID": {
                "idValue": "RBT"
            },
            "externalReference": "RBT",
            "certificationDescription": "Trekkerrijbewijs T",
            "itemID": "RBT"
        }
    ]
}