{
	"info": {
		"_postman_id": "216a80c8-e969-48c9-9f6c-93ce38bb4ecd",
		"name": "BB Time Off Requests",
		"schema": "https://schema.getpostman.com/json/collection/v2.1.0/collection.json"
	},
	"item": [
		{
			"name": "Access token",
			"request": {
				"method": "POST",
				"header": [],
				"body": {
					"mode": "urlencoded",
					"urlencoded": [
						{
							"key": "grant_type",
							"value": "client_credentials",
							"type": "text"
						},
						{
							"key": "client_id",
							"value": "paste client_id here",
							"type": "text"
						},
						{
							"key": "client_secret",
							"value": "paste client_secret here",
							"type": "text"
						}
					]
				},
				"url": {
					"raw": "https://iat-accounts.eu.adp.com/auth/oauth/v2/token",
					"protocol": "https",
					"host": [
						"iat-accounts",
						"eu",
						"adp",
						"com"
					],
					"path": [
						"auth",
						"oauth",
						"v2",
						"token"
					]
				}
			},
			"response": []
		},
		{
			"name": "Retrieve the time off requests using $filter parameter",
			"protocolProfileBehavior": {
				"disableBodyPruning": true
			},
			"request": {
				"auth": {
					"type": "bearer",
					"bearer": [
						{
							"key": "token",
							"value": "paste bearer token here",
							"type": "string"
						}
					]
				},
				"method": "GET",
				"header": [
					{
						"key": "adp.env",
						"value": "DEV",
						"type": "text",
						"disabled": true
					},
					{
						"key": "Content-Type",
						"name": "Content-Type",
						"value": "application/x-www-form-urlencoded",
						"type": "text"
					}
				],
				"body": {
					"mode": "urlencoded",
					"urlencoded": []
				},
				"url": {
					"raw": "https://iat-accounts.eu.adp.com/time/v3/workers/000084/leave-time-off-requests?$filter=/timeOffRequests/timeOffEntries/datePeriod/startDate ge '2020-07-01' and /timeOffRequests/timeOffEntries/datePeriod/endDate lt '2020-07-31'",
					"protocol": "https",
					"host": [
						"iat-accounts",
						"eu",
						"adp",
						"com"
					],
					"path": [
						"time",
						"v3",
						"workers",
						"000084",
						"leave-time-off-requests"
					],
					"query": [
						{
							"key": "$filter",
							"value": "/timeOffRequests/timeOffEntries/datePeriod/startDate ge '2020-07-01' and /timeOffRequests/timeOffEntries/datePeriod/endDate lt '2020-07-31'"
						}
					]
				}
			},
			"response": []
		},
		{
			"name": "A time off request for a certain date is cancelled",
			"protocolProfileBehavior": {
				"disableBodyPruning": true
			},
			"request": {
				"auth": {
					"type": "bearer",
					"bearer": [
						{
							"key": "token",
							"value": "paste bearer token here",
							"type": "string"
						}
					]
				},
				"method": "GET",
				"header": [
					{
						"key": "adp.env",
						"value": "DEV",
						"type": "text",
						"disabled": true
					},
					{
						"key": "Content-Type",
						"name": "Content-Type",
						"value": "application/x-www-form-urlencoded",
						"type": "text"
					}
				],
				"body": {
					"mode": "urlencoded",
					"urlencoded": []
				},
				"url": {
					"raw": "https://iat-accounts.eu.adp.com/events/time/v1/time-off-request.cancel/5fe103b2-fb04-4bef-ae1d-e4abdd235d79",
					"protocol": "https",
					"host": [
						"iat-accounts",
						"eu",
						"adp",
						"com"
					],
					"path": [
						"events",
						"time",
						"v1",
						"time-off-request.cancel",
						"5fe103b2-fb04-4bef-ae1d-e4abdd235d79"
					]
				}
			},
			"response": []
		},
		{
			"name": "A time off request for a certain date is submitted",
			"protocolProfileBehavior": {
				"disableBodyPruning": true
			},
			"request": {
				"auth": {
					"type": "bearer",
					"bearer": [
						{
							"key": "token",
							"value": "paste bearer token here",
							"type": "string"
						}
					]
				},
				"method": "GET",
				"header": [
					{
						"key": "adp.env",
						"value": "DEV",
						"type": "text",
						"disabled": true
					},
					{
						"key": "Content-Type",
						"name": "Content-Type",
						"value": "application/x-www-form-urlencoded",
						"type": "text"
					}
				],
				"body": {
					"mode": "urlencoded",
					"urlencoded": []
				},
				"url": {
					"raw": "https://iat-accounts.eu.adp.com/events/time/v1/time-off-request.submit/325ddecb-3564-432b-ba55-beff0873e245",
					"protocol": "https",
					"host": [
						"iat-accounts",
						"eu",
						"adp",
						"com"
					],
					"path": [
						"events",
						"time",
						"v1",
						"time-off-request.submit",
						"325ddecb-3564-432b-ba55-beff0873e245"
					]
				}
			},
			"response": []
		}
	],
	"protocolProfileBehavior": {}
}