{
    "events": [
        {
            "creationDateTime": "2020-12-29T00:00:00Z",
            "effectiveDateTime": "2020-12-28T00:00:00Z",
            "eventID": "de9ddeb7-1abd-4717-8c78-c39455b5247d",
            "eventNameCode": {
                "codeValue": "organizationRole.add"
            },
            "data": {
                "eventContext": {
                    "contextExpressionID": "000001"
                },
                "output": {
                    "organizationRole": {
                        "workerID": {
                            "idValue": "000001",
                            "schemeCode": {
                                "codeValue": "WF",
                                "longName": "Workforce"
                            }
                        },
                        "roleCode": {
                            "codeValue": "HOOFD"
                        },
                        "workerName": {
                            "formattedName": "NDS Burghout"
                        }
                    }
                }
            }
        }
    ]
}