{
   "events":[
      {
         "data":{
            "output":{
               "payDataInput":[
                  {
                     "payeePayInputs":[
                        {
                           "associateOID":"meverin-mp1",
                           "payPeriodStartDate":"2020-09-01",
                           "payrollProfilePayInputs":[
                              {
                                 "payInputs":[
                                    {
                                       "calculationFactorInputs":[
                                          {
                                             "calculationFactorCode":{
                                                "codeValue":"T729"
                                             },
                                             "calculationFactorRate":{
                                                "baseUnitCode":{
                                                   "codeValue":"ABC"
                                                }
                                             },
                                             "configurationTags":[
                                                {
                                                   "tagCode":""
                                                }
                                             ]
                                          }
                                       ]
                                    }
                                 ]
                              }
                           ]
                        }
                     ]
                  }
               ]
            }
         }
      }
   ],
   "confirmMessage":{
      "createDateTime":"2021-11-19T09:58:22.489+01:00",
      "protocolStatusCode":{
         "codeValue":"200"
      },
      "protocolCode":{
         
      },
      "requestStatusCode":{
         "codeValue":"succeeded"
      }
   }
}